pawn_pay/Exceptions.py
pawn_pay/__init__.py
pawn_pay/PawnDex/DataFlex.py
pawn_pay/PawnDex/__init__.py
pawn_pay/PawnMaster/__init__.py
pawn_pay/PawnMaster/models.py
pawn_pay/PawnMaster/unused_models.py
pawn_pay/helpers/Schema.py
pawn_pay/helpers/__init__.py
pawn_pay/helpers/configure.py
pawn_pay/helpers/logo.py
pawnpay-0.1.5.dist-info/LICENSE.txt
pawnpay-0.1.5.dist-info/METADATA
pawnpay-0.1.5.dist-info/WHEEL
pawnpay-0.1.5.dist-info/top_level.txt
pawnpay-0.1.5.dist-info/RECORD
